llama_index/llms/contextual/__init__.py
llama_index/llms/contextual/base.py
llama_index/llms/contextual/test-contextual.ipynb
llama_index_llms_contextual-0.1.1.dist-info/METADATA
llama_index_llms_contextual-0.1.1.dist-info/WHEEL
llama_index_llms_contextual-0.1.1.dist-info/RECORD
