Metadata-Version: 2.4
Name: llama-index-llms-contextual
Version: 0.1.1
Summary: llama-index contextual integration
Author-email: Sean Smith <sean.smith@contextual.ai>
License-Expression: MIT
Requires-Python: <4.0,>=3.9
Requires-Dist: contextual-client<0.5,>=0.4.0
Requires-Dist: llama-index-llms-openai-like<0.6,>=0.5.0
